sitemap_tool/__init__.py
sitemap_tool/add_urls_to_sitemap.py
sitemap_tool/check_duplicates.py
sitemap_tool/clean_urls.py
sitemap_tool/logging_config.py
sitemap_tool/main.py
sitemap_tool/remove_urls_from_sitemap.py
sitemap_tool-0.1.0.dist-info/METADATA
sitemap_tool-0.1.0.dist-info/WHEEL
sitemap_tool-0.1.0.dist-info/top_level.txt
sitemap_tool-0.1.0.dist-info/RECORD
