Metadata-Version: 2.4
Name: sitemap_tool
Version: 0.1.0
Summary: A tool for cleaning and managing sitemap URLs.
Author-email: Jubarte Labs <dev@jubartelabs.com>
License-Expression: MIT
Project-URL: Homepage, https://github.com/Jubarte-Labs/prj-carpets-sitemap-cleaning
Requires-Python: >=3.9
